{
  "A1": [
    {
      "en": "apple_0",
      "tr": "elma_0"
    },
    {
      "en": "book_1",
      "tr": "kitap_1"
    },
    {
      "en": "table_2",
      "tr": "masa_2"
    },
    {
      "en": "go_3",
      "tr": "gitmek_3"
    },
    {
      "en": "blue_4",
      "tr": "mavi_4"
    },
    {
      "en": "school_5",
      "tr": "okul_5"
    },
    {
      "en": "pen_6",
      "tr": "kalem_6"
    },
    {
      "en": "dog_7",
      "tr": "köpek_7"
    },
    {
      "en": "cat_8",
      "tr": "kedi_8"
    },
    {
      "en": "chair_9",
      "tr": "sandalye_9"
    },
    {
      "en": "run_10",
      "tr": "koşmak_10"
    },
    {
      "en": "eat_11",
      "tr": "yemek_11"
    },
    {
      "en": "drink_12",
      "tr": "içmek_12"
    },
    {
      "en": "big_13",
      "tr": "büyük_13"
    },
    {
      "en": "small_14",
      "tr": "küçük_14"
    },
    {
      "en": "house_15",
      "tr": "ev_15"
    },
    {
      "en": "car_16",
      "tr": "araba_16"
    },
    {
      "en": "yes_17",
      "tr": "evet_17"
    },
    {
      "en": "no_18",
      "tr": "hayır_18"
    },
    {
      "en": "water_19",
      "tr": "su_19"
    },
    {
      "en": "milk_20",
      "tr": "süt_20"
    },
    {
      "en": "bird_21",
      "tr": "kuş_21"
    },
    {
      "en": "fish_22",
      "tr": "balık_22"
    },
    {
      "en": "tree_23",
      "tr": "ağaç_23"
    },
    {
      "en": "sun_24",
      "tr": "güneş_24"
    },
    {
      "en": "sky_25",
      "tr": "gökyüzü_25"
    },
    {
      "en": "friend_26",
      "tr": "arkadaş_26"
    },
    {
      "en": "family_27",
      "tr": "aile_27"
    },
    {
      "en": "bed_28",
      "tr": "yatak_28"
    },
    {
      "en": "door_29",
      "tr": "kapı_29"
    },
    {
      "en": "travel_30",
      "tr": "seyahat etmek_30"
    },
    {
      "en": "happy_31",
      "tr": "mutlu_31"
    },
    {
      "en": "sad_32",
      "tr": "üzgün_32"
    },
    {
      "en": "money_33",
      "tr": "para_33"
    },
    {
      "en": "job_34",
      "tr": "iş_34"
    },
    {
      "en": "weather_35",
      "tr": "hava durumu_35"
    },
    {
      "en": "movie_36",
      "tr": "film_36"
    },
    {
      "en": "computer_37",
      "tr": "bilgisayar_37"
    },
    {
      "en": "weekend_38",
      "tr": "hafta sonu_38"
    },
    {
      "en": "clothes_39",
      "tr": "kıyafetler_39"
    },
    {
      "en": "food_40",
      "tr": "yemek_40"
    },
    {
      "en": "city_41",
      "tr": "şehir_41"
    },
    {
      "en": "country_42",
      "tr": "ülke_42"
    },
    {
      "en": "language_43",
      "tr": "dil_43"
    },
    {
      "en": "party_44",
      "tr": "parti_44"
    },
    {
      "en": "music_45",
      "tr": "müzik_45"
    },
    {
      "en": "cook_46",
      "tr": "yemek pişirmek_46"
    },
    {
      "en": "train_47",
      "tr": "tren_47"
    },
    {
      "en": "phone_48",
      "tr": "telefon_48"
    },
    {
      "en": "garden_49",
      "tr": "bahçe_49"
    },
    {
      "en": "window_50",
      "tr": "pencere_50"
    },
    {
      "en": "restaurant_51",
      "tr": "restoran_51"
    },
    {
      "en": "holiday_52",
      "tr": "tatil_52"
    },
    {
      "en": "market_53",
      "tr": "pazar_53"
    },
    {
      "en": "beach_54",
      "tr": "sahil_54"
    },
    {
      "en": "hospital_55",
      "tr": "hastane_55"
    },
    {
      "en": "airport_56",
      "tr": "havaalanı_56"
    },
    {
      "en": "station_57",
      "tr": "istasyon_57"
    },
    {
      "en": "minute_58",
      "tr": "dakika_58"
    },
    {
      "en": "street_59",
      "tr": "sokak_59"
    },
    {
      "en": "light_60",
      "tr": "ışık_60"
    },
    {
      "en": "dark_61",
      "tr": "karanlık_61"
    },
    {
      "en": "music_62",
      "tr": "müzik_62"
    },
    {
      "en": "apple_63",
      "tr": "elma_63"
    },
    {
      "en": "book_64",
      "tr": "kitap_64"
    },
    {
      "en": "table_65",
      "tr": "masa_65"
    },
    {
      "en": "go_66",
      "tr": "gitmek_66"
    },
    {
      "en": "blue_67",
      "tr": "mavi_67"
    },
    {
      "en": "school_68",
      "tr": "okul_68"
    },
    {
      "en": "pen_69",
      "tr": "kalem_69"
    },
    {
      "en": "dog_70",
      "tr": "köpek_70"
    },
    {
      "en": "cat_71",
      "tr": "kedi_71"
    },
    {
      "en": "chair_72",
      "tr": "sandalye_72"
    },
    {
      "en": "run_73",
      "tr": "koşmak_73"
    },
    {
      "en": "eat_74",
      "tr": "yemek_74"
    },
    {
      "en": "drink_75",
      "tr": "içmek_75"
    },
    {
      "en": "big_76",
      "tr": "büyük_76"
    },
    {
      "en": "small_77",
      "tr": "küçük_77"
    },
    {
      "en": "house_78",
      "tr": "ev_78"
    },
    {
      "en": "car_79",
      "tr": "araba_79"
    },
    {
      "en": "yes_80",
      "tr": "evet_80"
    },
    {
      "en": "no_81",
      "tr": "hayır_81"
    },
    {
      "en": "water_82",
      "tr": "su_82"
    },
    {
      "en": "milk_83",
      "tr": "süt_83"
    },
    {
      "en": "bird_84",
      "tr": "kuş_84"
    },
    {
      "en": "fish_85",
      "tr": "balık_85"
    },
    {
      "en": "tree_86",
      "tr": "ağaç_86"
    },
    {
      "en": "sun_87",
      "tr": "güneş_87"
    },
    {
      "en": "sky_88",
      "tr": "gökyüzü_88"
    },
    {
      "en": "friend_89",
      "tr": "arkadaş_89"
    },
    {
      "en": "family_90",
      "tr": "aile_90"
    },
    {
      "en": "bed_91",
      "tr": "yatak_91"
    },
    {
      "en": "door_92",
      "tr": "kapı_92"
    },
    {
      "en": "travel_93",
      "tr": "seyahat etmek_93"
    },
    {
      "en": "happy_94",
      "tr": "mutlu_94"
    },
    {
      "en": "sad_95",
      "tr": "üzgün_95"
    },
    {
      "en": "money_96",
      "tr": "para_96"
    },
    {
      "en": "job_97",
      "tr": "iş_97"
    },
    {
      "en": "weather_98",
      "tr": "hava durumu_98"
    },
    {
      "en": "movie_99",
      "tr": "film_99"
    },
    {
      "en": "computer_100",
      "tr": "bilgisayar_100"
    },
    {
      "en": "weekend_101",
      "tr": "hafta sonu_101"
    },
    {
      "en": "clothes_102",
      "tr": "kıyafetler_102"
    },
    {
      "en": "food_103",
      "tr": "yemek_103"
    },
    {
      "en": "city_104",
      "tr": "şehir_104"
    },
    {
      "en": "country_105",
      "tr": "ülke_105"
    },
    {
      "en": "language_106",
      "tr": "dil_106"
    },
    {
      "en": "party_107",
      "tr": "parti_107"
    },
    {
      "en": "music_108",
      "tr": "müzik_108"
    },
    {
      "en": "cook_109",
      "tr": "yemek pişirmek_109"
    },
    {
      "en": "train_110",
      "tr": "tren_110"
    },
    {
      "en": "phone_111",
      "tr": "telefon_111"
    },
    {
      "en": "garden_112",
      "tr": "bahçe_112"
    },
    {
      "en": "window_113",
      "tr": "pencere_113"
    },
    {
      "en": "restaurant_114",
      "tr": "restoran_114"
    },
    {
      "en": "holiday_115",
      "tr": "tatil_115"
    },
    {
      "en": "market_116",
      "tr": "pazar_116"
    },
    {
      "en": "beach_117",
      "tr": "sahil_117"
    },
    {
      "en": "hospital_118",
      "tr": "hastane_118"
    },
    {
      "en": "airport_119",
      "tr": "havaalanı_119"
    },
    {
      "en": "station_120",
      "tr": "istasyon_120"
    },
    {
      "en": "minute_121",
      "tr": "dakika_121"
    },
    {
      "en": "street_122",
      "tr": "sokak_122"
    },
    {
      "en": "light_123",
      "tr": "ışık_123"
    },
    {
      "en": "dark_124",
      "tr": "karanlık_124"
    },
    {
      "en": "music_125",
      "tr": "müzik_125"
    },
    {
      "en": "apple_126",
      "tr": "elma_126"
    },
    {
      "en": "book_127",
      "tr": "kitap_127"
    },
    {
      "en": "table_128",
      "tr": "masa_128"
    },
    {
      "en": "go_129",
      "tr": "gitmek_129"
    },
    {
      "en": "blue_130",
      "tr": "mavi_130"
    },
    {
      "en": "school_131",
      "tr": "okul_131"
    },
    {
      "en": "pen_132",
      "tr": "kalem_132"
    },
    {
      "en": "dog_133",
      "tr": "köpek_133"
    },
    {
      "en": "cat_134",
      "tr": "kedi_134"
    },
    {
      "en": "chair_135",
      "tr": "sandalye_135"
    },
    {
      "en": "run_136",
      "tr": "koşmak_136"
    },
    {
      "en": "eat_137",
      "tr": "yemek_137"
    },
    {
      "en": "drink_138",
      "tr": "içmek_138"
    },
    {
      "en": "big_139",
      "tr": "büyük_139"
    },
    {
      "en": "small_140",
      "tr": "küçük_140"
    },
    {
      "en": "house_141",
      "tr": "ev_141"
    },
    {
      "en": "car_142",
      "tr": "araba_142"
    },
    {
      "en": "yes_143",
      "tr": "evet_143"
    },
    {
      "en": "no_144",
      "tr": "hayır_144"
    },
    {
      "en": "water_145",
      "tr": "su_145"
    },
    {
      "en": "milk_146",
      "tr": "süt_146"
    },
    {
      "en": "bird_147",
      "tr": "kuş_147"
    },
    {
      "en": "fish_148",
      "tr": "balık_148"
    },
    {
      "en": "tree_149",
      "tr": "ağaç_149"
    },
    {
      "en": "sun_150",
      "tr": "güneş_150"
    },
    {
      "en": "sky_151",
      "tr": "gökyüzü_151"
    },
    {
      "en": "friend_152",
      "tr": "arkadaş_152"
    },
    {
      "en": "family_153",
      "tr": "aile_153"
    },
    {
      "en": "bed_154",
      "tr": "yatak_154"
    },
    {
      "en": "door_155",
      "tr": "kapı_155"
    },
    {
      "en": "travel_156",
      "tr": "seyahat etmek_156"
    },
    {
      "en": "happy_157",
      "tr": "mutlu_157"
    },
    {
      "en": "sad_158",
      "tr": "üzgün_158"
    },
    {
      "en": "money_159",
      "tr": "para_159"
    },
    {
      "en": "job_160",
      "tr": "iş_160"
    },
    {
      "en": "weather_161",
      "tr": "hava durumu_161"
    },
    {
      "en": "movie_162",
      "tr": "film_162"
    },
    {
      "en": "computer_163",
      "tr": "bilgisayar_163"
    },
    {
      "en": "weekend_164",
      "tr": "hafta sonu_164"
    },
    {
      "en": "clothes_165",
      "tr": "kıyafetler_165"
    },
    {
      "en": "food_166",
      "tr": "yemek_166"
    },
    {
      "en": "city_167",
      "tr": "şehir_167"
    },
    {
      "en": "country_168",
      "tr": "ülke_168"
    },
    {
      "en": "language_169",
      "tr": "dil_169"
    },
    {
      "en": "party_170",
      "tr": "parti_170"
    },
    {
      "en": "music_171",
      "tr": "müzik_171"
    },
    {
      "en": "cook_172",
      "tr": "yemek pişirmek_172"
    },
    {
      "en": "train_173",
      "tr": "tren_173"
    },
    {
      "en": "phone_174",
      "tr": "telefon_174"
    },
    {
      "en": "garden_175",
      "tr": "bahçe_175"
    },
    {
      "en": "window_176",
      "tr": "pencere_176"
    },
    {
      "en": "restaurant_177",
      "tr": "restoran_177"
    },
    {
      "en": "holiday_178",
      "tr": "tatil_178"
    },
    {
      "en": "market_179",
      "tr": "pazar_179"
    },
    {
      "en": "beach_180",
      "tr": "sahil_180"
    },
    {
      "en": "hospital_181",
      "tr": "hastane_181"
    },
    {
      "en": "airport_182",
      "tr": "havaalanı_182"
    },
    {
      "en": "station_183",
      "tr": "istasyon_183"
    },
    {
      "en": "minute_184",
      "tr": "dakika_184"
    },
    {
      "en": "street_185",
      "tr": "sokak_185"
    },
    {
      "en": "light_186",
      "tr": "ışık_186"
    },
    {
      "en": "dark_187",
      "tr": "karanlık_187"
    },
    {
      "en": "music_188",
      "tr": "müzik_188"
    },
    {
      "en": "apple_189",
      "tr": "elma_189"
    },
    {
      "en": "book_190",
      "tr": "kitap_190"
    },
    {
      "en": "table_191",
      "tr": "masa_191"
    },
    {
      "en": "go_192",
      "tr": "gitmek_192"
    },
    {
      "en": "blue_193",
      "tr": "mavi_193"
    },
    {
      "en": "school_194",
      "tr": "okul_194"
    },
    {
      "en": "pen_195",
      "tr": "kalem_195"
    },
    {
      "en": "dog_196",
      "tr": "köpek_196"
    },
    {
      "en": "cat_197",
      "tr": "kedi_197"
    },
    {
      "en": "chair_198",
      "tr": "sandalye_198"
    },
    {
      "en": "run_199",
      "tr": "koşmak_199"
    }
  ],
  "A2": [
    {
      "en": "apple_0",
      "tr": "elma_0"
    },
    {
      "en": "book_1",
      "tr": "kitap_1"
    },
    {
      "en": "table_2",
      "tr": "masa_2"
    },
    {
      "en": "go_3",
      "tr": "gitmek_3"
    },
    {
      "en": "blue_4",
      "tr": "mavi_4"
    },
    {
      "en": "school_5",
      "tr": "okul_5"
    },
    {
      "en": "pen_6",
      "tr": "kalem_6"
    },
    {
      "en": "dog_7",
      "tr": "köpek_7"
    },
    {
      "en": "cat_8",
      "tr": "kedi_8"
    },
    {
      "en": "chair_9",
      "tr": "sandalye_9"
    },
    {
      "en": "run_10",
      "tr": "koşmak_10"
    },
    {
      "en": "eat_11",
      "tr": "yemek_11"
    },
    {
      "en": "drink_12",
      "tr": "içmek_12"
    },
    {
      "en": "big_13",
      "tr": "büyük_13"
    },
    {
      "en": "small_14",
      "tr": "küçük_14"
    },
    {
      "en": "house_15",
      "tr": "ev_15"
    },
    {
      "en": "car_16",
      "tr": "araba_16"
    },
    {
      "en": "yes_17",
      "tr": "evet_17"
    },
    {
      "en": "no_18",
      "tr": "hayır_18"
    },
    {
      "en": "water_19",
      "tr": "su_19"
    },
    {
      "en": "milk_20",
      "tr": "süt_20"
    },
    {
      "en": "bird_21",
      "tr": "kuş_21"
    },
    {
      "en": "fish_22",
      "tr": "balık_22"
    },
    {
      "en": "tree_23",
      "tr": "ağaç_23"
    },
    {
      "en": "sun_24",
      "tr": "güneş_24"
    },
    {
      "en": "sky_25",
      "tr": "gökyüzü_25"
    },
    {
      "en": "friend_26",
      "tr": "arkadaş_26"
    },
    {
      "en": "family_27",
      "tr": "aile_27"
    },
    {
      "en": "bed_28",
      "tr": "yatak_28"
    },
    {
      "en": "door_29",
      "tr": "kapı_29"
    },
    {
      "en": "travel_30",
      "tr": "seyahat etmek_30"
    },
    {
      "en": "happy_31",
      "tr": "mutlu_31"
    },
    {
      "en": "sad_32",
      "tr": "üzgün_32"
    },
    {
      "en": "money_33",
      "tr": "para_33"
    },
    {
      "en": "job_34",
      "tr": "iş_34"
    },
    {
      "en": "weather_35",
      "tr": "hava durumu_35"
    },
    {
      "en": "movie_36",
      "tr": "film_36"
    },
    {
      "en": "computer_37",
      "tr": "bilgisayar_37"
    },
    {
      "en": "weekend_38",
      "tr": "hafta sonu_38"
    },
    {
      "en": "clothes_39",
      "tr": "kıyafetler_39"
    },
    {
      "en": "food_40",
      "tr": "yemek_40"
    },
    {
      "en": "city_41",
      "tr": "şehir_41"
    },
    {
      "en": "country_42",
      "tr": "ülke_42"
    },
    {
      "en": "language_43",
      "tr": "dil_43"
    },
    {
      "en": "party_44",
      "tr": "parti_44"
    },
    {
      "en": "music_45",
      "tr": "müzik_45"
    },
    {
      "en": "cook_46",
      "tr": "yemek pişirmek_46"
    },
    {
      "en": "train_47",
      "tr": "tren_47"
    },
    {
      "en": "phone_48",
      "tr": "telefon_48"
    },
    {
      "en": "garden_49",
      "tr": "bahçe_49"
    },
    {
      "en": "window_50",
      "tr": "pencere_50"
    },
    {
      "en": "restaurant_51",
      "tr": "restoran_51"
    },
    {
      "en": "holiday_52",
      "tr": "tatil_52"
    },
    {
      "en": "market_53",
      "tr": "pazar_53"
    },
    {
      "en": "beach_54",
      "tr": "sahil_54"
    },
    {
      "en": "hospital_55",
      "tr": "hastane_55"
    },
    {
      "en": "airport_56",
      "tr": "havaalanı_56"
    },
    {
      "en": "station_57",
      "tr": "istasyon_57"
    },
    {
      "en": "minute_58",
      "tr": "dakika_58"
    },
    {
      "en": "street_59",
      "tr": "sokak_59"
    },
    {
      "en": "light_60",
      "tr": "ışık_60"
    },
    {
      "en": "dark_61",
      "tr": "karanlık_61"
    },
    {
      "en": "music_62",
      "tr": "müzik_62"
    },
    {
      "en": "apple_63",
      "tr": "elma_63"
    },
    {
      "en": "book_64",
      "tr": "kitap_64"
    },
    {
      "en": "table_65",
      "tr": "masa_65"
    },
    {
      "en": "go_66",
      "tr": "gitmek_66"
    },
    {
      "en": "blue_67",
      "tr": "mavi_67"
    },
    {
      "en": "school_68",
      "tr": "okul_68"
    },
    {
      "en": "pen_69",
      "tr": "kalem_69"
    },
    {
      "en": "dog_70",
      "tr": "köpek_70"
    },
    {
      "en": "cat_71",
      "tr": "kedi_71"
    },
    {
      "en": "chair_72",
      "tr": "sandalye_72"
    },
    {
      "en": "run_73",
      "tr": "koşmak_73"
    },
    {
      "en": "eat_74",
      "tr": "yemek_74"
    },
    {
      "en": "drink_75",
      "tr": "içmek_75"
    },
    {
      "en": "big_76",
      "tr": "büyük_76"
    },
    {
      "en": "small_77",
      "tr": "küçük_77"
    },
    {
      "en": "house_78",
      "tr": "ev_78"
    },
    {
      "en": "car_79",
      "tr": "araba_79"
    },
    {
      "en": "yes_80",
      "tr": "evet_80"
    },
    {
      "en": "no_81",
      "tr": "hayır_81"
    },
    {
      "en": "water_82",
      "tr": "su_82"
    },
    {
      "en": "milk_83",
      "tr": "süt_83"
    },
    {
      "en": "bird_84",
      "tr": "kuş_84"
    },
    {
      "en": "fish_85",
      "tr": "balık_85"
    },
    {
      "en": "tree_86",
      "tr": "ağaç_86"
    },
    {
      "en": "sun_87",
      "tr": "güneş_87"
    },
    {
      "en": "sky_88",
      "tr": "gökyüzü_88"
    },
    {
      "en": "friend_89",
      "tr": "arkadaş_89"
    },
    {
      "en": "family_90",
      "tr": "aile_90"
    },
    {
      "en": "bed_91",
      "tr": "yatak_91"
    },
    {
      "en": "door_92",
      "tr": "kapı_92"
    },
    {
      "en": "travel_93",
      "tr": "seyahat etmek_93"
    },
    {
      "en": "happy_94",
      "tr": "mutlu_94"
    },
    {
      "en": "sad_95",
      "tr": "üzgün_95"
    },
    {
      "en": "money_96",
      "tr": "para_96"
    },
    {
      "en": "job_97",
      "tr": "iş_97"
    },
    {
      "en": "weather_98",
      "tr": "hava durumu_98"
    },
    {
      "en": "movie_99",
      "tr": "film_99"
    },
    {
      "en": "computer_100",
      "tr": "bilgisayar_100"
    },
    {
      "en": "weekend_101",
      "tr": "hafta sonu_101"
    },
    {
      "en": "clothes_102",
      "tr": "kıyafetler_102"
    },
    {
      "en": "food_103",
      "tr": "yemek_103"
    },
    {
      "en": "city_104",
      "tr": "şehir_104"
    },
    {
      "en": "country_105",
      "tr": "ülke_105"
    },
    {
      "en": "language_106",
      "tr": "dil_106"
    },
    {
      "en": "party_107",
      "tr": "parti_107"
    },
    {
      "en": "music_108",
      "tr": "müzik_108"
    },
    {
      "en": "cook_109",
      "tr": "yemek pişirmek_109"
    },
    {
      "en": "train_110",
      "tr": "tren_110"
    },
    {
      "en": "phone_111",
      "tr": "telefon_111"
    },
    {
      "en": "garden_112",
      "tr": "bahçe_112"
    },
    {
      "en": "window_113",
      "tr": "pencere_113"
    },
    {
      "en": "restaurant_114",
      "tr": "restoran_114"
    },
    {
      "en": "holiday_115",
      "tr": "tatil_115"
    },
    {
      "en": "market_116",
      "tr": "pazar_116"
    },
    {
      "en": "beach_117",
      "tr": "sahil_117"
    },
    {
      "en": "hospital_118",
      "tr": "hastane_118"
    },
    {
      "en": "airport_119",
      "tr": "havaalanı_119"
    },
    {
      "en": "station_120",
      "tr": "istasyon_120"
    },
    {
      "en": "minute_121",
      "tr": "dakika_121"
    },
    {
      "en": "street_122",
      "tr": "sokak_122"
    },
    {
      "en": "light_123",
      "tr": "ışık_123"
    },
    {
      "en": "dark_124",
      "tr": "karanlık_124"
    },
    {
      "en": "music_125",
      "tr": "müzik_125"
    },
    {
      "en": "apple_126",
      "tr": "elma_126"
    },
    {
      "en": "book_127",
      "tr": "kitap_127"
    },
    {
      "en": "table_128",
      "tr": "masa_128"
    },
    {
      "en": "go_129",
      "tr": "gitmek_129"
    },
    {
      "en": "blue_130",
      "tr": "mavi_130"
    },
    {
      "en": "school_131",
      "tr": "okul_131"
    },
    {
      "en": "pen_132",
      "tr": "kalem_132"
    },
    {
      "en": "dog_133",
      "tr": "köpek_133"
    },
    {
      "en": "cat_134",
      "tr": "kedi_134"
    },
    {
      "en": "chair_135",
      "tr": "sandalye_135"
    },
    {
      "en": "run_136",
      "tr": "koşmak_136"
    },
    {
      "en": "eat_137",
      "tr": "yemek_137"
    },
    {
      "en": "drink_138",
      "tr": "içmek_138"
    },
    {
      "en": "big_139",
      "tr": "büyük_139"
    },
    {
      "en": "small_140",
      "tr": "küçük_140"
    },
    {
      "en": "house_141",
      "tr": "ev_141"
    },
    {
      "en": "car_142",
      "tr": "araba_142"
    },
    {
      "en": "yes_143",
      "tr": "evet_143"
    },
    {
      "en": "no_144",
      "tr": "hayır_144"
    },
    {
      "en": "water_145",
      "tr": "su_145"
    },
    {
      "en": "milk_146",
      "tr": "süt_146"
    },
    {
      "en": "bird_147",
      "tr": "kuş_147"
    },
    {
      "en": "fish_148",
      "tr": "balık_148"
    },
    {
      "en": "tree_149",
      "tr": "ağaç_149"
    },
    {
      "en": "sun_150",
      "tr": "güneş_150"
    },
    {
      "en": "sky_151",
      "tr": "gökyüzü_151"
    },
    {
      "en": "friend_152",
      "tr": "arkadaş_152"
    },
    {
      "en": "family_153",
      "tr": "aile_153"
    },
    {
      "en": "bed_154",
      "tr": "yatak_154"
    },
    {
      "en": "door_155",
      "tr": "kapı_155"
    },
    {
      "en": "travel_156",
      "tr": "seyahat etmek_156"
    },
    {
      "en": "happy_157",
      "tr": "mutlu_157"
    },
    {
      "en": "sad_158",
      "tr": "üzgün_158"
    },
    {
      "en": "money_159",
      "tr": "para_159"
    },
    {
      "en": "job_160",
      "tr": "iş_160"
    },
    {
      "en": "weather_161",
      "tr": "hava durumu_161"
    },
    {
      "en": "movie_162",
      "tr": "film_162"
    },
    {
      "en": "computer_163",
      "tr": "bilgisayar_163"
    },
    {
      "en": "weekend_164",
      "tr": "hafta sonu_164"
    },
    {
      "en": "clothes_165",
      "tr": "kıyafetler_165"
    },
    {
      "en": "food_166",
      "tr": "yemek_166"
    },
    {
      "en": "city_167",
      "tr": "şehir_167"
    },
    {
      "en": "country_168",
      "tr": "ülke_168"
    },
    {
      "en": "language_169",
      "tr": "dil_169"
    },
    {
      "en": "party_170",
      "tr": "parti_170"
    },
    {
      "en": "music_171",
      "tr": "müzik_171"
    },
    {
      "en": "cook_172",
      "tr": "yemek pişirmek_172"
    },
    {
      "en": "train_173",
      "tr": "tren_173"
    },
    {
      "en": "phone_174",
      "tr": "telefon_174"
    },
    {
      "en": "garden_175",
      "tr": "bahçe_175"
    },
    {
      "en": "window_176",
      "tr": "pencere_176"
    },
    {
      "en": "restaurant_177",
      "tr": "restoran_177"
    },
    {
      "en": "holiday_178",
      "tr": "tatil_178"
    },
    {
      "en": "market_179",
      "tr": "pazar_179"
    },
    {
      "en": "beach_180",
      "tr": "sahil_180"
    },
    {
      "en": "hospital_181",
      "tr": "hastane_181"
    },
    {
      "en": "airport_182",
      "tr": "havaalanı_182"
    },
    {
      "en": "station_183",
      "tr": "istasyon_183"
    },
    {
      "en": "minute_184",
      "tr": "dakika_184"
    },
    {
      "en": "street_185",
      "tr": "sokak_185"
    },
    {
      "en": "light_186",
      "tr": "ışık_186"
    },
    {
      "en": "dark_187",
      "tr": "karanlık_187"
    },
    {
      "en": "music_188",
      "tr": "müzik_188"
    },
    {
      "en": "apple_189",
      "tr": "elma_189"
    },
    {
      "en": "book_190",
      "tr": "kitap_190"
    },
    {
      "en": "table_191",
      "tr": "masa_191"
    },
    {
      "en": "go_192",
      "tr": "gitmek_192"
    },
    {
      "en": "blue_193",
      "tr": "mavi_193"
    },
    {
      "en": "school_194",
      "tr": "okul_194"
    },
    {
      "en": "pen_195",
      "tr": "kalem_195"
    },
    {
      "en": "dog_196",
      "tr": "köpek_196"
    },
    {
      "en": "cat_197",
      "tr": "kedi_197"
    },
    {
      "en": "chair_198",
      "tr": "sandalye_198"
    },
    {
      "en": "run_199",
      "tr": "koşmak_199"
    }
  ],
  "B1": [
    {
      "en": "apple_0",
      "tr": "elma_0"
    },
    {
      "en": "book_1",
      "tr": "kitap_1"
    },
    {
      "en": "table_2",
      "tr": "masa_2"
    },
    {
      "en": "go_3",
      "tr": "gitmek_3"
    },
    {
      "en": "blue_4",
      "tr": "mavi_4"
    },
    {
      "en": "school_5",
      "tr": "okul_5"
    },
    {
      "en": "pen_6",
      "tr": "kalem_6"
    },
    {
      "en": "dog_7",
      "tr": "köpek_7"
    },
    {
      "en": "cat_8",
      "tr": "kedi_8"
    },
    {
      "en": "chair_9",
      "tr": "sandalye_9"
    },
    {
      "en": "run_10",
      "tr": "koşmak_10"
    },
    {
      "en": "eat_11",
      "tr": "yemek_11"
    },
    {
      "en": "drink_12",
      "tr": "içmek_12"
    },
    {
      "en": "big_13",
      "tr": "büyük_13"
    },
    {
      "en": "small_14",
      "tr": "küçük_14"
    },
    {
      "en": "house_15",
      "tr": "ev_15"
    },
    {
      "en": "car_16",
      "tr": "araba_16"
    },
    {
      "en": "yes_17",
      "tr": "evet_17"
    },
    {
      "en": "no_18",
      "tr": "hayır_18"
    },
    {
      "en": "water_19",
      "tr": "su_19"
    },
    {
      "en": "milk_20",
      "tr": "süt_20"
    },
    {
      "en": "bird_21",
      "tr": "kuş_21"
    },
    {
      "en": "fish_22",
      "tr": "balık_22"
    },
    {
      "en": "tree_23",
      "tr": "ağaç_23"
    },
    {
      "en": "sun_24",
      "tr": "güneş_24"
    },
    {
      "en": "sky_25",
      "tr": "gökyüzü_25"
    },
    {
      "en": "friend_26",
      "tr": "arkadaş_26"
    },
    {
      "en": "family_27",
      "tr": "aile_27"
    },
    {
      "en": "bed_28",
      "tr": "yatak_28"
    },
    {
      "en": "door_29",
      "tr": "kapı_29"
    },
    {
      "en": "travel_30",
      "tr": "seyahat etmek_30"
    },
    {
      "en": "happy_31",
      "tr": "mutlu_31"
    },
    {
      "en": "sad_32",
      "tr": "üzgün_32"
    },
    {
      "en": "money_33",
      "tr": "para_33"
    },
    {
      "en": "job_34",
      "tr": "iş_34"
    },
    {
      "en": "weather_35",
      "tr": "hava durumu_35"
    },
    {
      "en": "movie_36",
      "tr": "film_36"
    },
    {
      "en": "computer_37",
      "tr": "bilgisayar_37"
    },
    {
      "en": "weekend_38",
      "tr": "hafta sonu_38"
    },
    {
      "en": "clothes_39",
      "tr": "kıyafetler_39"
    },
    {
      "en": "food_40",
      "tr": "yemek_40"
    },
    {
      "en": "city_41",
      "tr": "şehir_41"
    },
    {
      "en": "country_42",
      "tr": "ülke_42"
    },
    {
      "en": "language_43",
      "tr": "dil_43"
    },
    {
      "en": "party_44",
      "tr": "parti_44"
    },
    {
      "en": "music_45",
      "tr": "müzik_45"
    },
    {
      "en": "cook_46",
      "tr": "yemek pişirmek_46"
    },
    {
      "en": "train_47",
      "tr": "tren_47"
    },
    {
      "en": "phone_48",
      "tr": "telefon_48"
    },
    {
      "en": "garden_49",
      "tr": "bahçe_49"
    },
    {
      "en": "window_50",
      "tr": "pencere_50"
    },
    {
      "en": "restaurant_51",
      "tr": "restoran_51"
    },
    {
      "en": "holiday_52",
      "tr": "tatil_52"
    },
    {
      "en": "market_53",
      "tr": "pazar_53"
    },
    {
      "en": "beach_54",
      "tr": "sahil_54"
    },
    {
      "en": "hospital_55",
      "tr": "hastane_55"
    },
    {
      "en": "airport_56",
      "tr": "havaalanı_56"
    },
    {
      "en": "station_57",
      "tr": "istasyon_57"
    },
    {
      "en": "minute_58",
      "tr": "dakika_58"
    },
    {
      "en": "street_59",
      "tr": "sokak_59"
    },
    {
      "en": "light_60",
      "tr": "ışık_60"
    },
    {
      "en": "dark_61",
      "tr": "karanlık_61"
    },
    {
      "en": "music_62",
      "tr": "müzik_62"
    },
    {
      "en": "apple_63",
      "tr": "elma_63"
    },
    {
      "en": "book_64",
      "tr": "kitap_64"
    },
    {
      "en": "table_65",
      "tr": "masa_65"
    },
    {
      "en": "go_66",
      "tr": "gitmek_66"
    },
    {
      "en": "blue_67",
      "tr": "mavi_67"
    },
    {
      "en": "school_68",
      "tr": "okul_68"
    },
    {
      "en": "pen_69",
      "tr": "kalem_69"
    },
    {
      "en": "dog_70",
      "tr": "köpek_70"
    },
    {
      "en": "cat_71",
      "tr": "kedi_71"
    },
    {
      "en": "chair_72",
      "tr": "sandalye_72"
    },
    {
      "en": "run_73",
      "tr": "koşmak_73"
    },
    {
      "en": "eat_74",
      "tr": "yemek_74"
    },
    {
      "en": "drink_75",
      "tr": "içmek_75"
    },
    {
      "en": "big_76",
      "tr": "büyük_76"
    },
    {
      "en": "small_77",
      "tr": "küçük_77"
    },
    {
      "en": "house_78",
      "tr": "ev_78"
    },
    {
      "en": "car_79",
      "tr": "araba_79"
    },
    {
      "en": "yes_80",
      "tr": "evet_80"
    },
    {
      "en": "no_81",
      "tr": "hayır_81"
    },
    {
      "en": "water_82",
      "tr": "su_82"
    },
    {
      "en": "milk_83",
      "tr": "süt_83"
    },
    {
      "en": "bird_84",
      "tr": "kuş_84"
    },
    {
      "en": "fish_85",
      "tr": "balık_85"
    },
    {
      "en": "tree_86",
      "tr": "ağaç_86"
    },
    {
      "en": "sun_87",
      "tr": "güneş_87"
    },
    {
      "en": "sky_88",
      "tr": "gökyüzü_88"
    },
    {
      "en": "friend_89",
      "tr": "arkadaş_89"
    },
    {
      "en": "family_90",
      "tr": "aile_90"
    },
    {
      "en": "bed_91",
      "tr": "yatak_91"
    },
    {
      "en": "door_92",
      "tr": "kapı_92"
    },
    {
      "en": "travel_93",
      "tr": "seyahat etmek_93"
    },
    {
      "en": "happy_94",
      "tr": "mutlu_94"
    },
    {
      "en": "sad_95",
      "tr": "üzgün_95"
    },
    {
      "en": "money_96",
      "tr": "para_96"
    },
    {
      "en": "job_97",
      "tr": "iş_97"
    },
    {
      "en": "weather_98",
      "tr": "hava durumu_98"
    },
    {
      "en": "movie_99",
      "tr": "film_99"
    },
    {
      "en": "computer_100",
      "tr": "bilgisayar_100"
    },
    {
      "en": "weekend_101",
      "tr": "hafta sonu_101"
    },
    {
      "en": "clothes_102",
      "tr": "kıyafetler_102"
    },
    {
      "en": "food_103",
      "tr": "yemek_103"
    },
    {
      "en": "city_104",
      "tr": "şehir_104"
    },
    {
      "en": "country_105",
      "tr": "ülke_105"
    },
    {
      "en": "language_106",
      "tr": "dil_106"
    },
    {
      "en": "party_107",
      "tr": "parti_107"
    },
    {
      "en": "music_108",
      "tr": "müzik_108"
    },
    {
      "en": "cook_109",
      "tr": "yemek pişirmek_109"
    },
    {
      "en": "train_110",
      "tr": "tren_110"
    },
    {
      "en": "phone_111",
      "tr": "telefon_111"
    },
    {
      "en": "garden_112",
      "tr": "bahçe_112"
    },
    {
      "en": "window_113",
      "tr": "pencere_113"
    },
    {
      "en": "restaurant_114",
      "tr": "restoran_114"
    },
    {
      "en": "holiday_115",
      "tr": "tatil_115"
    },
    {
      "en": "market_116",
      "tr": "pazar_116"
    },
    {
      "en": "beach_117",
      "tr": "sahil_117"
    },
    {
      "en": "hospital_118",
      "tr": "hastane_118"
    },
    {
      "en": "airport_119",
      "tr": "havaalanı_119"
    },
    {
      "en": "station_120",
      "tr": "istasyon_120"
    },
    {
      "en": "minute_121",
      "tr": "dakika_121"
    },
    {
      "en": "street_122",
      "tr": "sokak_122"
    },
    {
      "en": "light_123",
      "tr": "ışık_123"
    },
    {
      "en": "dark_124",
      "tr": "karanlık_124"
    },
    {
      "en": "music_125",
      "tr": "müzik_125"
    },
    {
      "en": "apple_126",
      "tr": "elma_126"
    },
    {
      "en": "book_127",
      "tr": "kitap_127"
    },
    {
      "en": "table_128",
      "tr": "masa_128"
    },
    {
      "en": "go_129",
      "tr": "gitmek_129"
    },
    {
      "en": "blue_130",
      "tr": "mavi_130"
    },
    {
      "en": "school_131",
      "tr": "okul_131"
    },
    {
      "en": "pen_132",
      "tr": "kalem_132"
    },
    {
      "en": "dog_133",
      "tr": "köpek_133"
    },
    {
      "en": "cat_134",
      "tr": "kedi_134"
    },
    {
      "en": "chair_135",
      "tr": "sandalye_135"
    },
    {
      "en": "run_136",
      "tr": "koşmak_136"
    },
    {
      "en": "eat_137",
      "tr": "yemek_137"
    },
    {
      "en": "drink_138",
      "tr": "içmek_138"
    },
    {
      "en": "big_139",
      "tr": "büyük_139"
    },
    {
      "en": "small_140",
      "tr": "küçük_140"
    },
    {
      "en": "house_141",
      "tr": "ev_141"
    },
    {
      "en": "car_142",
      "tr": "araba_142"
    },
    {
      "en": "yes_143",
      "tr": "evet_143"
    },
    {
      "en": "no_144",
      "tr": "hayır_144"
    },
    {
      "en": "water_145",
      "tr": "su_145"
    },
    {
      "en": "milk_146",
      "tr": "süt_146"
    },
    {
      "en": "bird_147",
      "tr": "kuş_147"
    },
    {
      "en": "fish_148",
      "tr": "balık_148"
    },
    {
      "en": "tree_149",
      "tr": "ağaç_149"
    },
    {
      "en": "sun_150",
      "tr": "güneş_150"
    },
    {
      "en": "sky_151",
      "tr": "gökyüzü_151"
    },
    {
      "en": "friend_152",
      "tr": "arkadaş_152"
    },
    {
      "en": "family_153",
      "tr": "aile_153"
    },
    {
      "en": "bed_154",
      "tr": "yatak_154"
    },
    {
      "en": "door_155",
      "tr": "kapı_155"
    },
    {
      "en": "travel_156",
      "tr": "seyahat etmek_156"
    },
    {
      "en": "happy_157",
      "tr": "mutlu_157"
    },
    {
      "en": "sad_158",
      "tr": "üzgün_158"
    },
    {
      "en": "money_159",
      "tr": "para_159"
    },
    {
      "en": "job_160",
      "tr": "iş_160"
    },
    {
      "en": "weather_161",
      "tr": "hava durumu_161"
    },
    {
      "en": "movie_162",
      "tr": "film_162"
    },
    {
      "en": "computer_163",
      "tr": "bilgisayar_163"
    },
    {
      "en": "weekend_164",
      "tr": "hafta sonu_164"
    },
    {
      "en": "clothes_165",
      "tr": "kıyafetler_165"
    },
    {
      "en": "food_166",
      "tr": "yemek_166"
    },
    {
      "en": "city_167",
      "tr": "şehir_167"
    },
    {
      "en": "country_168",
      "tr": "ülke_168"
    },
    {
      "en": "language_169",
      "tr": "dil_169"
    },
    {
      "en": "party_170",
      "tr": "parti_170"
    },
    {
      "en": "music_171",
      "tr": "müzik_171"
    },
    {
      "en": "cook_172",
      "tr": "yemek pişirmek_172"
    },
    {
      "en": "train_173",
      "tr": "tren_173"
    },
    {
      "en": "phone_174",
      "tr": "telefon_174"
    },
    {
      "en": "garden_175",
      "tr": "bahçe_175"
    },
    {
      "en": "window_176",
      "tr": "pencere_176"
    },
    {
      "en": "restaurant_177",
      "tr": "restoran_177"
    },
    {
      "en": "holiday_178",
      "tr": "tatil_178"
    },
    {
      "en": "market_179",
      "tr": "pazar_179"
    },
    {
      "en": "beach_180",
      "tr": "sahil_180"
    },
    {
      "en": "hospital_181",
      "tr": "hastane_181"
    },
    {
      "en": "airport_182",
      "tr": "havaalanı_182"
    },
    {
      "en": "station_183",
      "tr": "istasyon_183"
    },
    {
      "en": "minute_184",
      "tr": "dakika_184"
    },
    {
      "en": "street_185",
      "tr": "sokak_185"
    },
    {
      "en": "light_186",
      "tr": "ışık_186"
    },
    {
      "en": "dark_187",
      "tr": "karanlık_187"
    },
    {
      "en": "music_188",
      "tr": "müzik_188"
    },
    {
      "en": "apple_189",
      "tr": "elma_189"
    },
    {
      "en": "book_190",
      "tr": "kitap_190"
    },
    {
      "en": "table_191",
      "tr": "masa_191"
    },
    {
      "en": "go_192",
      "tr": "gitmek_192"
    },
    {
      "en": "blue_193",
      "tr": "mavi_193"
    },
    {
      "en": "school_194",
      "tr": "okul_194"
    },
    {
      "en": "pen_195",
      "tr": "kalem_195"
    },
    {
      "en": "dog_196",
      "tr": "köpek_196"
    },
    {
      "en": "cat_197",
      "tr": "kedi_197"
    },
    {
      "en": "chair_198",
      "tr": "sandalye_198"
    },
    {
      "en": "run_199",
      "tr": "koşmak_199"
    }
  ],
  "B2": [
    {
      "en": "apple_0",
      "tr": "elma_0"
    },
    {
      "en": "book_1",
      "tr": "kitap_1"
    },
    {
      "en": "table_2",
      "tr": "masa_2"
    },
    {
      "en": "go_3",
      "tr": "gitmek_3"
    },
    {
      "en": "blue_4",
      "tr": "mavi_4"
    },
    {
      "en": "school_5",
      "tr": "okul_5"
    },
    {
      "en": "pen_6",
      "tr": "kalem_6"
    },
    {
      "en": "dog_7",
      "tr": "köpek_7"
    },
    {
      "en": "cat_8",
      "tr": "kedi_8"
    },
    {
      "en": "chair_9",
      "tr": "sandalye_9"
    },
    {
      "en": "run_10",
      "tr": "koşmak_10"
    },
    {
      "en": "eat_11",
      "tr": "yemek_11"
    },
    {
      "en": "drink_12",
      "tr": "içmek_12"
    },
    {
      "en": "big_13",
      "tr": "büyük_13"
    },
    {
      "en": "small_14",
      "tr": "küçük_14"
    },
    {
      "en": "house_15",
      "tr": "ev_15"
    },
    {
      "en": "car_16",
      "tr": "araba_16"
    },
    {
      "en": "yes_17",
      "tr": "evet_17"
    },
    {
      "en": "no_18",
      "tr": "hayır_18"
    },
    {
      "en": "water_19",
      "tr": "su_19"
    },
    {
      "en": "milk_20",
      "tr": "süt_20"
    },
    {
      "en": "bird_21",
      "tr": "kuş_21"
    },
    {
      "en": "fish_22",
      "tr": "balık_22"
    },
    {
      "en": "tree_23",
      "tr": "ağaç_23"
    },
    {
      "en": "sun_24",
      "tr": "güneş_24"
    },
    {
      "en": "sky_25",
      "tr": "gökyüzü_25"
    },
    {
      "en": "friend_26",
      "tr": "arkadaş_26"
    },
    {
      "en": "family_27",
      "tr": "aile_27"
    },
    {
      "en": "bed_28",
      "tr": "yatak_28"
    },
    {
      "en": "door_29",
      "tr": "kapı_29"
    },
    {
      "en": "travel_30",
      "tr": "seyahat etmek_30"
    },
    {
      "en": "happy_31",
      "tr": "mutlu_31"
    },
    {
      "en": "sad_32",
      "tr": "üzgün_32"
    },
    {
      "en": "money_33",
      "tr": "para_33"
    },
    {
      "en": "job_34",
      "tr": "iş_34"
    },
    {
      "en": "weather_35",
      "tr": "hava durumu_35"
    },
    {
      "en": "movie_36",
      "tr": "film_36"
    },
    {
      "en": "computer_37",
      "tr": "bilgisayar_37"
    },
    {
      "en": "weekend_38",
      "tr": "hafta sonu_38"
    },
    {
      "en": "clothes_39",
      "tr": "kıyafetler_39"
    },
    {
      "en": "food_40",
      "tr": "yemek_40"
    },
    {
      "en": "city_41",
      "tr": "şehir_41"
    },
    {
      "en": "country_42",
      "tr": "ülke_42"
    },
    {
      "en": "language_43",
      "tr": "dil_43"
    },
    {
      "en": "party_44",
      "tr": "parti_44"
    },
    {
      "en": "music_45",
      "tr": "müzik_45"
    },
    {
      "en": "cook_46",
      "tr": "yemek pişirmek_46"
    },
    {
      "en": "train_47",
      "tr": "tren_47"
    },
    {
      "en": "phone_48",
      "tr": "telefon_48"
    },
    {
      "en": "garden_49",
      "tr": "bahçe_49"
    },
    {
      "en": "window_50",
      "tr": "pencere_50"
    },
    {
      "en": "restaurant_51",
      "tr": "restoran_51"
    },
    {
      "en": "holiday_52",
      "tr": "tatil_52"
    },
    {
      "en": "market_53",
      "tr": "pazar_53"
    },
    {
      "en": "beach_54",
      "tr": "sahil_54"
    },
    {
      "en": "hospital_55",
      "tr": "hastane_55"
    },
    {
      "en": "airport_56",
      "tr": "havaalanı_56"
    },
    {
      "en": "station_57",
      "tr": "istasyon_57"
    },
    {
      "en": "minute_58",
      "tr": "dakika_58"
    },
    {
      "en": "street_59",
      "tr": "sokak_59"
    },
    {
      "en": "light_60",
      "tr": "ışık_60"
    },
    {
      "en": "dark_61",
      "tr": "karanlık_61"
    },
    {
      "en": "music_62",
      "tr": "müzik_62"
    },
    {
      "en": "apple_63",
      "tr": "elma_63"
    },
    {
      "en": "book_64",
      "tr": "kitap_64"
    },
    {
      "en": "table_65",
      "tr": "masa_65"
    },
    {
      "en": "go_66",
      "tr": "gitmek_66"
    },
    {
      "en": "blue_67",
      "tr": "mavi_67"
    },
    {
      "en": "school_68",
      "tr": "okul_68"
    },
    {
      "en": "pen_69",
      "tr": "kalem_69"
    },
    {
      "en": "dog_70",
      "tr": "köpek_70"
    },
    {
      "en": "cat_71",
      "tr": "kedi_71"
    },
    {
      "en": "chair_72",
      "tr": "sandalye_72"
    },
    {
      "en": "run_73",
      "tr": "koşmak_73"
    },
    {
      "en": "eat_74",
      "tr": "yemek_74"
    },
    {
      "en": "drink_75",
      "tr": "içmek_75"
    },
    {
      "en": "big_76",
      "tr": "büyük_76"
    },
    {
      "en": "small_77",
      "tr": "küçük_77"
    },
    {
      "en": "house_78",
      "tr": "ev_78"
    },
    {
      "en": "car_79",
      "tr": "araba_79"
    },
    {
      "en": "yes_80",
      "tr": "evet_80"
    },
    {
      "en": "no_81",
      "tr": "hayır_81"
    },
    {
      "en": "water_82",
      "tr": "su_82"
    },
    {
      "en": "milk_83",
      "tr": "süt_83"
    },
    {
      "en": "bird_84",
      "tr": "kuş_84"
    },
    {
      "en": "fish_85",
      "tr": "balık_85"
    },
    {
      "en": "tree_86",
      "tr": "ağaç_86"
    },
    {
      "en": "sun_87",
      "tr": "güneş_87"
    },
    {
      "en": "sky_88",
      "tr": "gökyüzü_88"
    },
    {
      "en": "friend_89",
      "tr": "arkadaş_89"
    },
    {
      "en": "family_90",
      "tr": "aile_90"
    },
    {
      "en": "bed_91",
      "tr": "yatak_91"
    },
    {
      "en": "door_92",
      "tr": "kapı_92"
    },
    {
      "en": "travel_93",
      "tr": "seyahat etmek_93"
    },
    {
      "en": "happy_94",
      "tr": "mutlu_94"
    },
    {
      "en": "sad_95",
      "tr": "üzgün_95"
    },
    {
      "en": "money_96",
      "tr": "para_96"
    },
    {
      "en": "job_97",
      "tr": "iş_97"
    },
    {
      "en": "weather_98",
      "tr": "hava durumu_98"
    },
    {
      "en": "movie_99",
      "tr": "film_99"
    },
    {
      "en": "computer_100",
      "tr": "bilgisayar_100"
    },
    {
      "en": "weekend_101",
      "tr": "hafta sonu_101"
    },
    {
      "en": "clothes_102",
      "tr": "kıyafetler_102"
    },
    {
      "en": "food_103",
      "tr": "yemek_103"
    },
    {
      "en": "city_104",
      "tr": "şehir_104"
    },
    {
      "en": "country_105",
      "tr": "ülke_105"
    },
    {
      "en": "language_106",
      "tr": "dil_106"
    },
    {
      "en": "party_107",
      "tr": "parti_107"
    },
    {
      "en": "music_108",
      "tr": "müzik_108"
    },
    {
      "en": "cook_109",
      "tr": "yemek pişirmek_109"
    },
    {
      "en": "train_110",
      "tr": "tren_110"
    },
    {
      "en": "phone_111",
      "tr": "telefon_111"
    },
    {
      "en": "garden_112",
      "tr": "bahçe_112"
    },
    {
      "en": "window_113",
      "tr": "pencere_113"
    },
    {
      "en": "restaurant_114",
      "tr": "restoran_114"
    },
    {
      "en": "holiday_115",
      "tr": "tatil_115"
    },
    {
      "en": "market_116",
      "tr": "pazar_116"
    },
    {
      "en": "beach_117",
      "tr": "sahil_117"
    },
    {
      "en": "hospital_118",
      "tr": "hastane_118"
    },
    {
      "en": "airport_119",
      "tr": "havaalanı_119"
    },
    {
      "en": "station_120",
      "tr": "istasyon_120"
    },
    {
      "en": "minute_121",
      "tr": "dakika_121"
    },
    {
      "en": "street_122",
      "tr": "sokak_122"
    },
    {
      "en": "light_123",
      "tr": "ışık_123"
    },
    {
      "en": "dark_124",
      "tr": "karanlık_124"
    },
    {
      "en": "music_125",
      "tr": "müzik_125"
    },
    {
      "en": "apple_126",
      "tr": "elma_126"
    },
    {
      "en": "book_127",
      "tr": "kitap_127"
    },
    {
      "en": "table_128",
      "tr": "masa_128"
    },
    {
      "en": "go_129",
      "tr": "gitmek_129"
    },
    {
      "en": "blue_130",
      "tr": "mavi_130"
    },
    {
      "en": "school_131",
      "tr": "okul_131"
    },
    {
      "en": "pen_132",
      "tr": "kalem_132"
    },
    {
      "en": "dog_133",
      "tr": "köpek_133"
    },
    {
      "en": "cat_134",
      "tr": "kedi_134"
    },
    {
      "en": "chair_135",
      "tr": "sandalye_135"
    },
    {
      "en": "run_136",
      "tr": "koşmak_136"
    },
    {
      "en": "eat_137",
      "tr": "yemek_137"
    },
    {
      "en": "drink_138",
      "tr": "içmek_138"
    },
    {
      "en": "big_139",
      "tr": "büyük_139"
    },
    {
      "en": "small_140",
      "tr": "küçük_140"
    },
    {
      "en": "house_141",
      "tr": "ev_141"
    },
    {
      "en": "car_142",
      "tr": "araba_142"
    },
    {
      "en": "yes_143",
      "tr": "evet_143"
    },
    {
      "en": "no_144",
      "tr": "hayır_144"
    },
    {
      "en": "water_145",
      "tr": "su_145"
    },
    {
      "en": "milk_146",
      "tr": "süt_146"
    },
    {
      "en": "bird_147",
      "tr": "kuş_147"
    },
    {
      "en": "fish_148",
      "tr": "balık_148"
    },
    {
      "en": "tree_149",
      "tr": "ağaç_149"
    },
    {
      "en": "sun_150",
      "tr": "güneş_150"
    },
    {
      "en": "sky_151",
      "tr": "gökyüzü_151"
    },
    {
      "en": "friend_152",
      "tr": "arkadaş_152"
    },
    {
      "en": "family_153",
      "tr": "aile_153"
    },
    {
      "en": "bed_154",
      "tr": "yatak_154"
    },
    {
      "en": "door_155",
      "tr": "kapı_155"
    },
    {
      "en": "travel_156",
      "tr": "seyahat etmek_156"
    },
    {
      "en": "happy_157",
      "tr": "mutlu_157"
    },
    {
      "en": "sad_158",
      "tr": "üzgün_158"
    },
    {
      "en": "money_159",
      "tr": "para_159"
    },
    {
      "en": "job_160",
      "tr": "iş_160"
    },
    {
      "en": "weather_161",
      "tr": "hava durumu_161"
    },
    {
      "en": "movie_162",
      "tr": "film_162"
    },
    {
      "en": "computer_163",
      "tr": "bilgisayar_163"
    },
    {
      "en": "weekend_164",
      "tr": "hafta sonu_164"
    },
    {
      "en": "clothes_165",
      "tr": "kıyafetler_165"
    },
    {
      "en": "food_166",
      "tr": "yemek_166"
    },
    {
      "en": "city_167",
      "tr": "şehir_167"
    },
    {
      "en": "country_168",
      "tr": "ülke_168"
    },
    {
      "en": "language_169",
      "tr": "dil_169"
    },
    {
      "en": "party_170",
      "tr": "parti_170"
    },
    {
      "en": "music_171",
      "tr": "müzik_171"
    },
    {
      "en": "cook_172",
      "tr": "yemek pişirmek_172"
    },
    {
      "en": "train_173",
      "tr": "tren_173"
    },
    {
      "en": "phone_174",
      "tr": "telefon_174"
    },
    {
      "en": "garden_175",
      "tr": "bahçe_175"
    },
    {
      "en": "window_176",
      "tr": "pencere_176"
    },
    {
      "en": "restaurant_177",
      "tr": "restoran_177"
    },
    {
      "en": "holiday_178",
      "tr": "tatil_178"
    },
    {
      "en": "market_179",
      "tr": "pazar_179"
    },
    {
      "en": "beach_180",
      "tr": "sahil_180"
    },
    {
      "en": "hospital_181",
      "tr": "hastane_181"
    },
    {
      "en": "airport_182",
      "tr": "havaalanı_182"
    },
    {
      "en": "station_183",
      "tr": "istasyon_183"
    },
    {
      "en": "minute_184",
      "tr": "dakika_184"
    },
    {
      "en": "street_185",
      "tr": "sokak_185"
    },
    {
      "en": "light_186",
      "tr": "ışık_186"
    },
    {
      "en": "dark_187",
      "tr": "karanlık_187"
    },
    {
      "en": "music_188",
      "tr": "müzik_188"
    },
    {
      "en": "apple_189",
      "tr": "elma_189"
    },
    {
      "en": "book_190",
      "tr": "kitap_190"
    },
    {
      "en": "table_191",
      "tr": "masa_191"
    },
    {
      "en": "go_192",
      "tr": "gitmek_192"
    },
    {
      "en": "blue_193",
      "tr": "mavi_193"
    },
    {
      "en": "school_194",
      "tr": "okul_194"
    },
    {
      "en": "pen_195",
      "tr": "kalem_195"
    },
    {
      "en": "dog_196",
      "tr": "köpek_196"
    },
    {
      "en": "cat_197",
      "tr": "kedi_197"
    },
    {
      "en": "chair_198",
      "tr": "sandalye_198"
    },
    {
      "en": "run_199",
      "tr": "koşmak_199"
    }
  ],
  "C1": [
    {
      "en": "apple_0",
      "tr": "elma_0"
    },
    {
      "en": "book_1",
      "tr": "kitap_1"
    },
    {
      "en": "table_2",
      "tr": "masa_2"
    },
    {
      "en": "go_3",
      "tr": "gitmek_3"
    },
    {
      "en": "blue_4",
      "tr": "mavi_4"
    },
    {
      "en": "school_5",
      "tr": "okul_5"
    },
    {
      "en": "pen_6",
      "tr": "kalem_6"
    },
    {
      "en": "dog_7",
      "tr": "köpek_7"
    },
    {
      "en": "cat_8",
      "tr": "kedi_8"
    },
    {
      "en": "chair_9",
      "tr": "sandalye_9"
    },
    {
      "en": "run_10",
      "tr": "koşmak_10"
    },
    {
      "en": "eat_11",
      "tr": "yemek_11"
    },
    {
      "en": "drink_12",
      "tr": "içmek_12"
    },
    {
      "en": "big_13",
      "tr": "büyük_13"
    },
    {
      "en": "small_14",
      "tr": "küçük_14"
    },
    {
      "en": "house_15",
      "tr": "ev_15"
    },
    {
      "en": "car_16",
      "tr": "araba_16"
    },
    {
      "en": "yes_17",
      "tr": "evet_17"
    },
    {
      "en": "no_18",
      "tr": "hayır_18"
    },
    {
      "en": "water_19",
      "tr": "su_19"
    },
    {
      "en": "milk_20",
      "tr": "süt_20"
    },
    {
      "en": "bird_21",
      "tr": "kuş_21"
    },
    {
      "en": "fish_22",
      "tr": "balık_22"
    },
    {
      "en": "tree_23",
      "tr": "ağaç_23"
    },
    {
      "en": "sun_24",
      "tr": "güneş_24"
    },
    {
      "en": "sky_25",
      "tr": "gökyüzü_25"
    },
    {
      "en": "friend_26",
      "tr": "arkadaş_26"
    },
    {
      "en": "family_27",
      "tr": "aile_27"
    },
    {
      "en": "bed_28",
      "tr": "yatak_28"
    },
    {
      "en": "door_29",
      "tr": "kapı_29"
    },
    {
      "en": "travel_30",
      "tr": "seyahat etmek_30"
    },
    {
      "en": "happy_31",
      "tr": "mutlu_31"
    },
    {
      "en": "sad_32",
      "tr": "üzgün_32"
    },
    {
      "en": "money_33",
      "tr": "para_33"
    },
    {
      "en": "job_34",
      "tr": "iş_34"
    },
    {
      "en": "weather_35",
      "tr": "hava durumu_35"
    },
    {
      "en": "movie_36",
      "tr": "film_36"
    },
    {
      "en": "computer_37",
      "tr": "bilgisayar_37"
    },
    {
      "en": "weekend_38",
      "tr": "hafta sonu_38"
    },
    {
      "en": "clothes_39",
      "tr": "kıyafetler_39"
    },
    {
      "en": "food_40",
      "tr": "yemek_40"
    },
    {
      "en": "city_41",
      "tr": "şehir_41"
    },
    {
      "en": "country_42",
      "tr": "ülke_42"
    },
    {
      "en": "language_43",
      "tr": "dil_43"
    },
    {
      "en": "party_44",
      "tr": "parti_44"
    },
    {
      "en": "music_45",
      "tr": "müzik_45"
    },
    {
      "en": "cook_46",
      "tr": "yemek pişirmek_46"
    },
    {
      "en": "train_47",
      "tr": "tren_47"
    },
    {
      "en": "phone_48",
      "tr": "telefon_48"
    },
    {
      "en": "garden_49",
      "tr": "bahçe_49"
    },
    {
      "en": "window_50",
      "tr": "pencere_50"
    },
    {
      "en": "restaurant_51",
      "tr": "restoran_51"
    },
    {
      "en": "holiday_52",
      "tr": "tatil_52"
    },
    {
      "en": "market_53",
      "tr": "pazar_53"
    },
    {
      "en": "beach_54",
      "tr": "sahil_54"
    },
    {
      "en": "hospital_55",
      "tr": "hastane_55"
    },
    {
      "en": "airport_56",
      "tr": "havaalanı_56"
    },
    {
      "en": "station_57",
      "tr": "istasyon_57"
    },
    {
      "en": "minute_58",
      "tr": "dakika_58"
    },
    {
      "en": "street_59",
      "tr": "sokak_59"
    },
    {
      "en": "light_60",
      "tr": "ışık_60"
    },
    {
      "en": "dark_61",
      "tr": "karanlık_61"
    },
    {
      "en": "music_62",
      "tr": "müzik_62"
    },
    {
      "en": "apple_63",
      "tr": "elma_63"
    },
    {
      "en": "book_64",
      "tr": "kitap_64"
    },
    {
      "en": "table_65",
      "tr": "masa_65"
    },
    {
      "en": "go_66",
      "tr": "gitmek_66"
    },
    {
      "en": "blue_67",
      "tr": "mavi_67"
    },
    {
      "en": "school_68",
      "tr": "okul_68"
    },
    {
      "en": "pen_69",
      "tr": "kalem_69"
    },
    {
      "en": "dog_70",
      "tr": "köpek_70"
    },
    {
      "en": "cat_71",
      "tr": "kedi_71"
    },
    {
      "en": "chair_72",
      "tr": "sandalye_72"
    },
    {
      "en": "run_73",
      "tr": "koşmak_73"
    },
    {
      "en": "eat_74",
      "tr": "yemek_74"
    },
    {
      "en": "drink_75",
      "tr": "içmek_75"
    },
    {
      "en": "big_76",
      "tr": "büyük_76"
    },
    {
      "en": "small_77",
      "tr": "küçük_77"
    },
    {
      "en": "house_78",
      "tr": "ev_78"
    },
    {
      "en": "car_79",
      "tr": "araba_79"
    },
    {
      "en": "yes_80",
      "tr": "evet_80"
    },
    {
      "en": "no_81",
      "tr": "hayır_81"
    },
    {
      "en": "water_82",
      "tr": "su_82"
    },
    {
      "en": "milk_83",
      "tr": "süt_83"
    },
    {
      "en": "bird_84",
      "tr": "kuş_84"
    },
    {
      "en": "fish_85",
      "tr": "balık_85"
    },
    {
      "en": "tree_86",
      "tr": "ağaç_86"
    },
    {
      "en": "sun_87",
      "tr": "güneş_87"
    },
    {
      "en": "sky_88",
      "tr": "gökyüzü_88"
    },
    {
      "en": "friend_89",
      "tr": "arkadaş_89"
    },
    {
      "en": "family_90",
      "tr": "aile_90"
    },
    {
      "en": "bed_91",
      "tr": "yatak_91"
    },
    {
      "en": "door_92",
      "tr": "kapı_92"
    },
    {
      "en": "travel_93",
      "tr": "seyahat etmek_93"
    },
    {
      "en": "happy_94",
      "tr": "mutlu_94"
    },
    {
      "en": "sad_95",
      "tr": "üzgün_95"
    },
    {
      "en": "money_96",
      "tr": "para_96"
    },
    {
      "en": "job_97",
      "tr": "iş_97"
    },
    {
      "en": "weather_98",
      "tr": "hava durumu_98"
    },
    {
      "en": "movie_99",
      "tr": "film_99"
    },
    {
      "en": "computer_100",
      "tr": "bilgisayar_100"
    },
    {
      "en": "weekend_101",
      "tr": "hafta sonu_101"
    },
    {
      "en": "clothes_102",
      "tr": "kıyafetler_102"
    },
    {
      "en": "food_103",
      "tr": "yemek_103"
    },
    {
      "en": "city_104",
      "tr": "şehir_104"
    },
    {
      "en": "country_105",
      "tr": "ülke_105"
    },
    {
      "en": "language_106",
      "tr": "dil_106"
    },
    {
      "en": "party_107",
      "tr": "parti_107"
    },
    {
      "en": "music_108",
      "tr": "müzik_108"
    },
    {
      "en": "cook_109",
      "tr": "yemek pişirmek_109"
    },
    {
      "en": "train_110",
      "tr": "tren_110"
    },
    {
      "en": "phone_111",
      "tr": "telefon_111"
    },
    {
      "en": "garden_112",
      "tr": "bahçe_112"
    },
    {
      "en": "window_113",
      "tr": "pencere_113"
    },
    {
      "en": "restaurant_114",
      "tr": "restoran_114"
    },
    {
      "en": "holiday_115",
      "tr": "tatil_115"
    },
    {
      "en": "market_116",
      "tr": "pazar_116"
    },
    {
      "en": "beach_117",
      "tr": "sahil_117"
    },
    {
      "en": "hospital_118",
      "tr": "hastane_118"
    },
    {
      "en": "airport_119",
      "tr": "havaalanı_119"
    },
    {
      "en": "station_120",
      "tr": "istasyon_120"
    },
    {
      "en": "minute_121",
      "tr": "dakika_121"
    },
    {
      "en": "street_122",
      "tr": "sokak_122"
    },
    {
      "en": "light_123",
      "tr": "ışık_123"
    },
    {
      "en": "dark_124",
      "tr": "karanlık_124"
    },
    {
      "en": "music_125",
      "tr": "müzik_125"
    },
    {
      "en": "apple_126",
      "tr": "elma_126"
    },
    {
      "en": "book_127",
      "tr": "kitap_127"
    },
    {
      "en": "table_128",
      "tr": "masa_128"
    },
    {
      "en": "go_129",
      "tr": "gitmek_129"
    },
    {
      "en": "blue_130",
      "tr": "mavi_130"
    },
    {
      "en": "school_131",
      "tr": "okul_131"
    },
    {
      "en": "pen_132",
      "tr": "kalem_132"
    },
    {
      "en": "dog_133",
      "tr": "köpek_133"
    },
    {
      "en": "cat_134",
      "tr": "kedi_134"
    },
    {
      "en": "chair_135",
      "tr": "sandalye_135"
    },
    {
      "en": "run_136",
      "tr": "koşmak_136"
    },
    {
      "en": "eat_137",
      "tr": "yemek_137"
    },
    {
      "en": "drink_138",
      "tr": "içmek_138"
    },
    {
      "en": "big_139",
      "tr": "büyük_139"
    },
    {
      "en": "small_140",
      "tr": "küçük_140"
    },
    {
      "en": "house_141",
      "tr": "ev_141"
    },
    {
      "en": "car_142",
      "tr": "araba_142"
    },
    {
      "en": "yes_143",
      "tr": "evet_143"
    },
    {
      "en": "no_144",
      "tr": "hayır_144"
    },
    {
      "en": "water_145",
      "tr": "su_145"
    },
    {
      "en": "milk_146",
      "tr": "süt_146"
    },
    {
      "en": "bird_147",
      "tr": "kuş_147"
    },
    {
      "en": "fish_148",
      "tr": "balık_148"
    },
    {
      "en": "tree_149",
      "tr": "ağaç_149"
    },
    {
      "en": "sun_150",
      "tr": "güneş_150"
    },
    {
      "en": "sky_151",
      "tr": "gökyüzü_151"
    },
    {
      "en": "friend_152",
      "tr": "arkadaş_152"
    },
    {
      "en": "family_153",
      "tr": "aile_153"
    },
    {
      "en": "bed_154",
      "tr": "yatak_154"
    },
    {
      "en": "door_155",
      "tr": "kapı_155"
    },
    {
      "en": "travel_156",
      "tr": "seyahat etmek_156"
    },
    {
      "en": "happy_157",
      "tr": "mutlu_157"
    },
    {
      "en": "sad_158",
      "tr": "üzgün_158"
    },
    {
      "en": "money_159",
      "tr": "para_159"
    },
    {
      "en": "job_160",
      "tr": "iş_160"
    },
    {
      "en": "weather_161",
      "tr": "hava durumu_161"
    },
    {
      "en": "movie_162",
      "tr": "film_162"
    },
    {
      "en": "computer_163",
      "tr": "bilgisayar_163"
    },
    {
      "en": "weekend_164",
      "tr": "hafta sonu_164"
    },
    {
      "en": "clothes_165",
      "tr": "kıyafetler_165"
    },
    {
      "en": "food_166",
      "tr": "yemek_166"
    },
    {
      "en": "city_167",
      "tr": "şehir_167"
    },
    {
      "en": "country_168",
      "tr": "ülke_168"
    },
    {
      "en": "language_169",
      "tr": "dil_169"
    },
    {
      "en": "party_170",
      "tr": "parti_170"
    },
    {
      "en": "music_171",
      "tr": "müzik_171"
    },
    {
      "en": "cook_172",
      "tr": "yemek pişirmek_172"
    },
    {
      "en": "train_173",
      "tr": "tren_173"
    },
    {
      "en": "phone_174",
      "tr": "telefon_174"
    },
    {
      "en": "garden_175",
      "tr": "bahçe_175"
    },
    {
      "en": "window_176",
      "tr": "pencere_176"
    },
    {
      "en": "restaurant_177",
      "tr": "restoran_177"
    },
    {
      "en": "holiday_178",
      "tr": "tatil_178"
    },
    {
      "en": "market_179",
      "tr": "pazar_179"
    },
    {
      "en": "beach_180",
      "tr": "sahil_180"
    },
    {
      "en": "hospital_181",
      "tr": "hastane_181"
    },
    {
      "en": "airport_182",
      "tr": "havaalanı_182"
    },
    {
      "en": "station_183",
      "tr": "istasyon_183"
    },
    {
      "en": "minute_184",
      "tr": "dakika_184"
    },
    {
      "en": "street_185",
      "tr": "sokak_185"
    },
    {
      "en": "light_186",
      "tr": "ışık_186"
    },
    {
      "en": "dark_187",
      "tr": "karanlık_187"
    },
    {
      "en": "music_188",
      "tr": "müzik_188"
    },
    {
      "en": "apple_189",
      "tr": "elma_189"
    },
    {
      "en": "book_190",
      "tr": "kitap_190"
    },
    {
      "en": "table_191",
      "tr": "masa_191"
    },
    {
      "en": "go_192",
      "tr": "gitmek_192"
    },
    {
      "en": "blue_193",
      "tr": "mavi_193"
    },
    {
      "en": "school_194",
      "tr": "okul_194"
    },
    {
      "en": "pen_195",
      "tr": "kalem_195"
    },
    {
      "en": "dog_196",
      "tr": "köpek_196"
    },
    {
      "en": "cat_197",
      "tr": "kedi_197"
    },
    {
      "en": "chair_198",
      "tr": "sandalye_198"
    },
    {
      "en": "run_199",
      "tr": "koşmak_199"
    }
  ],
  "C2": [
    {
      "en": "apple_0",
      "tr": "elma_0"
    },
    {
      "en": "book_1",
      "tr": "kitap_1"
    },
    {
      "en": "table_2",
      "tr": "masa_2"
    },
    {
      "en": "go_3",
      "tr": "gitmek_3"
    },
    {
      "en": "blue_4",
      "tr": "mavi_4"
    },
    {
      "en": "school_5",
      "tr": "okul_5"
    },
    {
      "en": "pen_6",
      "tr": "kalem_6"
    },
    {
      "en": "dog_7",
      "tr": "köpek_7"
    },
    {
      "en": "cat_8",
      "tr": "kedi_8"
    },
    {
      "en": "chair_9",
      "tr": "sandalye_9"
    },
    {
      "en": "run_10",
      "tr": "koşmak_10"
    },
    {
      "en": "eat_11",
      "tr": "yemek_11"
    },
    {
      "en": "drink_12",
      "tr": "içmek_12"
    },
    {
      "en": "big_13",
      "tr": "büyük_13"
    },
    {
      "en": "small_14",
      "tr": "küçük_14"
    },
    {
      "en": "house_15",
      "tr": "ev_15"
    },
    {
      "en": "car_16",
      "tr": "araba_16"
    },
    {
      "en": "yes_17",
      "tr": "evet_17"
    },
    {
      "en": "no_18",
      "tr": "hayır_18"
    },
    {
      "en": "water_19",
      "tr": "su_19"
    },
    {
      "en": "milk_20",
      "tr": "süt_20"
    },
    {
      "en": "bird_21",
      "tr": "kuş_21"
    },
    {
      "en": "fish_22",
      "tr": "balık_22"
    },
    {
      "en": "tree_23",
      "tr": "ağaç_23"
    },
    {
      "en": "sun_24",
      "tr": "güneş_24"
    },
    {
      "en": "sky_25",
      "tr": "gökyüzü_25"
    },
    {
      "en": "friend_26",
      "tr": "arkadaş_26"
    },
    {
      "en": "family_27",
      "tr": "aile_27"
    },
    {
      "en": "bed_28",
      "tr": "yatak_28"
    },
    {
      "en": "door_29",
      "tr": "kapı_29"
    },
    {
      "en": "travel_30",
      "tr": "seyahat etmek_30"
    },
    {
      "en": "happy_31",
      "tr": "mutlu_31"
    },
    {
      "en": "sad_32",
      "tr": "üzgün_32"
    },
    {
      "en": "money_33",
      "tr": "para_33"
    },
    {
      "en": "job_34",
      "tr": "iş_34"
    },
    {
      "en": "weather_35",
      "tr": "hava durumu_35"
    },
    {
      "en": "movie_36",
      "tr": "film_36"
    },
    {
      "en": "computer_37",
      "tr": "bilgisayar_37"
    },
    {
      "en": "weekend_38",
      "tr": "hafta sonu_38"
    },
    {
      "en": "clothes_39",
      "tr": "kıyafetler_39"
    },
    {
      "en": "food_40",
      "tr": "yemek_40"
    },
    {
      "en": "city_41",
      "tr": "şehir_41"
    },
    {
      "en": "country_42",
      "tr": "ülke_42"
    },
    {
      "en": "language_43",
      "tr": "dil_43"
    },
    {
      "en": "party_44",
      "tr": "parti_44"
    },
    {
      "en": "music_45",
      "tr": "müzik_45"
    },
    {
      "en": "cook_46",
      "tr": "yemek pişirmek_46"
    },
    {
      "en": "train_47",
      "tr": "tren_47"
    },
    {
      "en": "phone_48",
      "tr": "telefon_48"
    },
    {
      "en": "garden_49",
      "tr": "bahçe_49"
    },
    {
      "en": "window_50",
      "tr": "pencere_50"
    },
    {
      "en": "restaurant_51",
      "tr": "restoran_51"
    },
    {
      "en": "holiday_52",
      "tr": "tatil_52"
    },
    {
      "en": "market_53",
      "tr": "pazar_53"
    },
    {
      "en": "beach_54",
      "tr": "sahil_54"
    },
    {
      "en": "hospital_55",
      "tr": "hastane_55"
    },
    {
      "en": "airport_56",
      "tr": "havaalanı_56"
    },
    {
      "en": "station_57",
      "tr": "istasyon_57"
    },
    {
      "en": "minute_58",
      "tr": "dakika_58"
    },
    {
      "en": "street_59",
      "tr": "sokak_59"
    },
    {
      "en": "light_60",
      "tr": "ışık_60"
    },
    {
      "en": "dark_61",
      "tr": "karanlık_61"
    },
    {
      "en": "music_62",
      "tr": "müzik_62"
    },
    {
      "en": "apple_63",
      "tr": "elma_63"
    },
    {
      "en": "book_64",
      "tr": "kitap_64"
    },
    {
      "en": "table_65",
      "tr": "masa_65"
    },
    {
      "en": "go_66",
      "tr": "gitmek_66"
    },
    {
      "en": "blue_67",
      "tr": "mavi_67"
    },
    {
      "en": "school_68",
      "tr": "okul_68"
    },
    {
      "en": "pen_69",
      "tr": "kalem_69"
    },
    {
      "en": "dog_70",
      "tr": "köpek_70"
    },
    {
      "en": "cat_71",
      "tr": "kedi_71"
    },
    {
      "en": "chair_72",
      "tr": "sandalye_72"
    },
    {
      "en": "run_73",
      "tr": "koşmak_73"
    },
    {
      "en": "eat_74",
      "tr": "yemek_74"
    },
    {
      "en": "drink_75",
      "tr": "içmek_75"
    },
    {
      "en": "big_76",
      "tr": "büyük_76"
    },
    {
      "en": "small_77",
      "tr": "küçük_77"
    },
    {
      "en": "house_78",
      "tr": "ev_78"
    },
    {
      "en": "car_79",
      "tr": "araba_79"
    },
    {
      "en": "yes_80",
      "tr": "evet_80"
    },
    {
      "en": "no_81",
      "tr": "hayır_81"
    },
    {
      "en": "water_82",
      "tr": "su_82"
    },
    {
      "en": "milk_83",
      "tr": "süt_83"
    },
    {
      "en": "bird_84",
      "tr": "kuş_84"
    },
    {
      "en": "fish_85",
      "tr": "balık_85"
    },
    {
      "en": "tree_86",
      "tr": "ağaç_86"
    },
    {
      "en": "sun_87",
      "tr": "güneş_87"
    },
    {
      "en": "sky_88",
      "tr": "gökyüzü_88"
    },
    {
      "en": "friend_89",
      "tr": "arkadaş_89"
    },
    {
      "en": "family_90",
      "tr": "aile_90"
    },
    {
      "en": "bed_91",
      "tr": "yatak_91"
    },
    {
      "en": "door_92",
      "tr": "kapı_92"
    },
    {
      "en": "travel_93",
      "tr": "seyahat etmek_93"
    },
    {
      "en": "happy_94",
      "tr": "mutlu_94"
    },
    {
      "en": "sad_95",
      "tr": "üzgün_95"
    },
    {
      "en": "money_96",
      "tr": "para_96"
    },
    {
      "en": "job_97",
      "tr": "iş_97"
    },
    {
      "en": "weather_98",
      "tr": "hava durumu_98"
    },
    {
      "en": "movie_99",
      "tr": "film_99"
    },
    {
      "en": "computer_100",
      "tr": "bilgisayar_100"
    },
    {
      "en": "weekend_101",
      "tr": "hafta sonu_101"
    },
    {
      "en": "clothes_102",
      "tr": "kıyafetler_102"
    },
    {
      "en": "food_103",
      "tr": "yemek_103"
    },
    {
      "en": "city_104",
      "tr": "şehir_104"
    },
    {
      "en": "country_105",
      "tr": "ülke_105"
    },
    {
      "en": "language_106",
      "tr": "dil_106"
    },
    {
      "en": "party_107",
      "tr": "parti_107"
    },
    {
      "en": "music_108",
      "tr": "müzik_108"
    },
    {
      "en": "cook_109",
      "tr": "yemek pişirmek_109"
    },
    {
      "en": "train_110",
      "tr": "tren_110"
    },
    {
      "en": "phone_111",
      "tr": "telefon_111"
    },
    {
      "en": "garden_112",
      "tr": "bahçe_112"
    },
    {
      "en": "window_113",
      "tr": "pencere_113"
    },
    {
      "en": "restaurant_114",
      "tr": "restoran_114"
    },
    {
      "en": "holiday_115",
      "tr": "tatil_115"
    },
    {
      "en": "market_116",
      "tr": "pazar_116"
    },
    {
      "en": "beach_117",
      "tr": "sahil_117"
    },
    {
      "en": "hospital_118",
      "tr": "hastane_118"
    },
    {
      "en": "airport_119",
      "tr": "havaalanı_119"
    },
    {
      "en": "station_120",
      "tr": "istasyon_120"
    },
    {
      "en": "minute_121",
      "tr": "dakika_121"
    },
    {
      "en": "street_122",
      "tr": "sokak_122"
    },
    {
      "en": "light_123",
      "tr": "ışık_123"
    },
    {
      "en": "dark_124",
      "tr": "karanlık_124"
    },
    {
      "en": "music_125",
      "tr": "müzik_125"
    },
    {
      "en": "apple_126",
      "tr": "elma_126"
    },
    {
      "en": "book_127",
      "tr": "kitap_127"
    },
    {
      "en": "table_128",
      "tr": "masa_128"
    },
    {
      "en": "go_129",
      "tr": "gitmek_129"
    },
    {
      "en": "blue_130",
      "tr": "mavi_130"
    },
    {
      "en": "school_131",
      "tr": "okul_131"
    },
    {
      "en": "pen_132",
      "tr": "kalem_132"
    },
    {
      "en": "dog_133",
      "tr": "köpek_133"
    },
    {
      "en": "cat_134",
      "tr": "kedi_134"
    },
    {
      "en": "chair_135",
      "tr": "sandalye_135"
    },
    {
      "en": "run_136",
      "tr": "koşmak_136"
    },
    {
      "en": "eat_137",
      "tr": "yemek_137"
    },
    {
      "en": "drink_138",
      "tr": "içmek_138"
    },
    {
      "en": "big_139",
      "tr": "büyük_139"
    },
    {
      "en": "small_140",
      "tr": "küçük_140"
    },
    {
      "en": "house_141",
      "tr": "ev_141"
    },
    {
      "en": "car_142",
      "tr": "araba_142"
    },
    {
      "en": "yes_143",
      "tr": "evet_143"
    },
    {
      "en": "no_144",
      "tr": "hayır_144"
    },
    {
      "en": "water_145",
      "tr": "su_145"
    },
    {
      "en": "milk_146",
      "tr": "süt_146"
    },
    {
      "en": "bird_147",
      "tr": "kuş_147"
    },
    {
      "en": "fish_148",
      "tr": "balık_148"
    },
    {
      "en": "tree_149",
      "tr": "ağaç_149"
    },
    {
      "en": "sun_150",
      "tr": "güneş_150"
    },
    {
      "en": "sky_151",
      "tr": "gökyüzü_151"
    },
    {
      "en": "friend_152",
      "tr": "arkadaş_152"
    },
    {
      "en": "family_153",
      "tr": "aile_153"
    },
    {
      "en": "bed_154",
      "tr": "yatak_154"
    },
    {
      "en": "door_155",
      "tr": "kapı_155"
    },
    {
      "en": "travel_156",
      "tr": "seyahat etmek_156"
    },
    {
      "en": "happy_157",
      "tr": "mutlu_157"
    },
    {
      "en": "sad_158",
      "tr": "üzgün_158"
    },
    {
      "en": "money_159",
      "tr": "para_159"
    },
    {
      "en": "job_160",
      "tr": "iş_160"
    },
    {
      "en": "weather_161",
      "tr": "hava durumu_161"
    },
    {
      "en": "movie_162",
      "tr": "film_162"
    },
    {
      "en": "computer_163",
      "tr": "bilgisayar_163"
    },
    {
      "en": "weekend_164",
      "tr": "hafta sonu_164"
    },
    {
      "en": "clothes_165",
      "tr": "kıyafetler_165"
    },
    {
      "en": "food_166",
      "tr": "yemek_166"
    },
    {
      "en": "city_167",
      "tr": "şehir_167"
    },
    {
      "en": "country_168",
      "tr": "ülke_168"
    },
    {
      "en": "language_169",
      "tr": "dil_169"
    },
    {
      "en": "party_170",
      "tr": "parti_170"
    },
    {
      "en": "music_171",
      "tr": "müzik_171"
    },
    {
      "en": "cook_172",
      "tr": "yemek pişirmek_172"
    },
    {
      "en": "train_173",
      "tr": "tren_173"
    },
    {
      "en": "phone_174",
      "tr": "telefon_174"
    },
    {
      "en": "garden_175",
      "tr": "bahçe_175"
    },
    {
      "en": "window_176",
      "tr": "pencere_176"
    },
    {
      "en": "restaurant_177",
      "tr": "restoran_177"
    },
    {
      "en": "holiday_178",
      "tr": "tatil_178"
    },
    {
      "en": "market_179",
      "tr": "pazar_179"
    },
    {
      "en": "beach_180",
      "tr": "sahil_180"
    },
    {
      "en": "hospital_181",
      "tr": "hastane_181"
    },
    {
      "en": "airport_182",
      "tr": "havaalanı_182"
    },
    {
      "en": "station_183",
      "tr": "istasyon_183"
    },
    {
      "en": "minute_184",
      "tr": "dakika_184"
    },
    {
      "en": "street_185",
      "tr": "sokak_185"
    },
    {
      "en": "light_186",
      "tr": "ışık_186"
    },
    {
      "en": "dark_187",
      "tr": "karanlık_187"
    },
    {
      "en": "music_188",
      "tr": "müzik_188"
    },
    {
      "en": "apple_189",
      "tr": "elma_189"
    },
    {
      "en": "book_190",
      "tr": "kitap_190"
    },
    {
      "en": "table_191",
      "tr": "masa_191"
    },
    {
      "en": "go_192",
      "tr": "gitmek_192"
    },
    {
      "en": "blue_193",
      "tr": "mavi_193"
    },
    {
      "en": "school_194",
      "tr": "okul_194"
    },
    {
      "en": "pen_195",
      "tr": "kalem_195"
    },
    {
      "en": "dog_196",
      "tr": "köpek_196"
    },
    {
      "en": "cat_197",
      "tr": "kedi_197"
    },
    {
      "en": "chair_198",
      "tr": "sandalye_198"
    },
    {
      "en": "run_199",
      "tr": "koşmak_199"
    }
  ]
}